rmtb/__init__.py
rmtb/bot.py
rmtb/wrapper.py
rmtb-0.1.2.dist-info/WHEEL
rmtb-0.1.2.dist-info/METADATA
rmtb-0.1.2.dist-info/RECORD
