Metadata-Version: 2.1
Name: rmtb
Version: 0.1.2
Summary: A simple library for making rmtb bots in python.
Author: Your Name
Author-email: you@example.com
Requires-Python: >=3.7,<4.0
Classifier: Programming Language :: Python :: 3
Classifier: Programming Language :: Python :: 3.10
Classifier: Programming Language :: Python :: 3.7
Classifier: Programming Language :: Python :: 3.8
Classifier: Programming Language :: Python :: 3.9
Requires-Dist: rel (>=0.4.7,<0.5.0)
Requires-Dist: websocket-client (>=1.3.2,<2.0.0)
